Metadata-Version: 1.1
Name: timesquare
Version: 0.0.1
Summary: Solve Quadratic Equations
Home-page: UNKNOWN
Author: Ilay Furst
Author-email: furstilay11@gmail.com
License: MIT
Keywords: quadratic
Platform: UNKNOWN
Classifier: Development Status :: 5 - Production/Stable
Classifier: Intended Audience :: Education
Classifier: Operating System :: Microsoft :: Windows :: Windows 10
Classifier: License :: OSI Approved :: MIT License
Classifier: Programming Language :: Python :: 3
